<annotation>
  <folder>input</folder>
  <filename>00232.jpg</filename>
  <path>c:\Users\ani\Desktop\Yolo-Training-GoogleColab\data_conversion\main\input\00232.jpg</path>
  <source>
    <database>Unknown</database>
  </source>
  <size>
    <width>600</width>
    <height>444</height>
    <depth>3</depth>
  </size>
  <segmented>0</segmented>
  <object>
    <name>Car</name>
    <pose>Unspecified</pose>
    <truncated>0</truncated>
    <difficult>0</difficult>
    <bndbox>
      <xmin>32</xmin>
      <ymin>157</ymin>
      <xmax>362</xmax>
      <ymax>408</ymax>
    </bndbox>
  </object>
  <object>
    <name>Car</name>
    <pose>Unspecified</pose>
    <truncated>0</truncated>
    <difficult>0</difficult>
    <bndbox>
      <xmin>392</xmin>
      <ymin>90</ymin>
      <xmax>544</xmax>
      <ymax>378</ymax>
    </bndbox>
  </object>
</annotation>
